{
  "nom": "millesens",
  "version": "2025.5.21",
  "securite": "1.public",
  "securityLevels": ["1.public", "2.prive", "3.protege"],
  "dependances": [
    {
      "name": "millesens",
      "archives": [
        {
          "src": "https://docker.maple.maceroc.com/archives/apps/millegrilles_millesens_typescript.2025.5.21.tar.gz",
          "digest": "4OQCIEDgsFvCB4i5QYjpGpUL1T3mGGetZQ00n+GIzPgQORUq",
          "location": "nginx:html/applications/millesens"
        }
      ]
    }
  ],
  "nginx": {
    "conf": [
      "millesens.location"
    ]
  },
  "web": {
    "links": [
      {
        "labels": {
          "fr": {"name": "MilleSens", "description": "Assistant pour appareils domestiques."},
          "en": {"name": "MilleSens", "description": "Home Assistant"}
        },
        "url": "https://${HOSTNAME}/millesens/",
        "securite": "1.public",
        "required_domains": ["MaitreDesCles", "SenseursPassifs"]
      }
    ]
  }
}
